LICENSE
MANIFEST.in
README.md
setup.py
nonebot_plugin_offline_mahjong_helper/__init__.py
nonebot_plugin_offline_mahjong_helper.egg-info/PKG-INFO
nonebot_plugin_offline_mahjong_helper.egg-info/SOURCES.txt
nonebot_plugin_offline_mahjong_helper.egg-info/dependency_links.txt
nonebot_plugin_offline_mahjong_helper.egg-info/requires.txt
nonebot_plugin_offline_mahjong_helper.egg-info/top_level.txt
nonebot_plugin_offline_mahjong_helper/appoint/__init__.py
nonebot_plugin_offline_mahjong_helper/appoint/schedule.py
nonebot_plugin_offline_mahjong_helper/appoint/utils.py
nonebot_plugin_offline_mahjong_helper/count/__init__.py
nonebot_plugin_offline_mahjong_helper/query/__init__.py
nonebot_plugin_offline_mahjong_helper/query/utils.py
nonebot_plugin_offline_mahjong_helper/query/template/style.css